vielcord/__init__.py
vielcord/__main__.py
vielcord/__session__.py
vielcord/__solver__.py
vielcord/__udcord__.py
vielcord/models/device.py
vielcord/models/dynamic.py
vielcord/models/websocket.py
vielcord-0.0.7.5.dist-info/licenses/LICENSE
vielcord-0.0.7.5.dist-info/METADATA
vielcord-0.0.7.5.dist-info/WHEEL
vielcord-0.0.7.5.dist-info/top_level.txt
vielcord-0.0.7.5.dist-info/RECORD
